AutomatedDrinkDispensingSystem/AppWindow.py
AutomatedDrinkDispensingSystem/ApplicationUserEditor.py
AutomatedDrinkDispensingSystem/CustomerWindow.py
AutomatedDrinkDispensingSystem/DrinkProfile.py
AutomatedDrinkDispensingSystem/DrinkProfileManager.py
AutomatedDrinkDispensingSystem/EmbeddedKeyboard.py
AutomatedDrinkDispensingSystem/EmployeeWindow.py
AutomatedDrinkDispensingSystem/KeyboardWindow.py
AutomatedDrinkDispensingSystem/LogManager.py
AutomatedDrinkDispensingSystem/LoginWindow.py
AutomatedDrinkDispensingSystem/MainApp.py
AutomatedDrinkDispensingSystem/PeripheralDevice.py
AutomatedDrinkDispensingSystem/__init__.py
AutomatedDrinkDispensingSystem/Old scripts/__init__.py
AutomatedDrinkDispensingSystem/Old scripts/callback_functions.py
AutomatedDrinkDispensingSystem/Old scripts/main_application.py
AutomatedDrinkDispensingSystem/resources/__init__.py
AutomatedDrinkDispensingSystem/resources/drink_profiles/__init_.py
AutomatedDrinkDispensingSystem/resources/drink_profiles/cuba_libre/cuba_libre.jpg
AutomatedDrinkDispensingSystem/resources/drink_profiles/cuba_libre/cuba_libre.txt
AutomatedDrinkDispensingSystem/resources/drink_profiles/daiquiri/daiquiri.jpg
AutomatedDrinkDispensingSystem/resources/drink_profiles/daiquiri/daiquiri.txt
AutomatedDrinkDispensingSystem/resources/drink_profiles/kamikaze/kamikaze.jpg
AutomatedDrinkDispensingSystem/resources/drink_profiles/kamikaze/kamikaze.txt
AutomatedDrinkDispensingSystem/resources/drink_profiles/long_island_iced_tea/long_island_iced_tea.jpg
AutomatedDrinkDispensingSystem/resources/drink_profiles/long_island_iced_tea/long_island_iced_tea.txt
AutomatedDrinkDispensingSystem/resources/drink_profiles/naval_gimlet/naval_gimlet.jpg
AutomatedDrinkDispensingSystem/resources/drink_profiles/naval_gimlet/naval_gimlet.txt
AutomatedDrinkDispensingSystem/resources/drink_profiles/rum_and_coke/rum_and_coke.jpg
AutomatedDrinkDispensingSystem/resources/drink_profiles/rum_and_coke/rum_and_coke.txt
AutomatedDrinkDispensingSystem-1.0a2.dist-info/DESCRIPTION.rst
AutomatedDrinkDispensingSystem-1.0a2.dist-info/METADATA
AutomatedDrinkDispensingSystem-1.0a2.dist-info/RECORD
AutomatedDrinkDispensingSystem-1.0a2.dist-info/WHEEL
AutomatedDrinkDispensingSystem-1.0a2.dist-info/metadata.json
AutomatedDrinkDispensingSystem-1.0a2.dist-info/top_level.txt
