Metadata-Version: 2.0
Name: AutomatedDrinkDispensingSystem
Version: 1.0a2
Summary: UNKNOWN
Home-page: https://github.com/ChrisBlanks/AutomatedDrinkDispensingSystem
Author: Chris Blanks
Author-email: christopherablanks@gmail.com
License: LICENSE.txt
Platform: Raspbian
Requires-Dist: cryptography (>=1.7.1)
Requires-Dist: setuptools (>=18.5)
